odoo/addons/partner_statement/README.rst
odoo/addons/partner_statement/__init__.py
odoo/addons/partner_statement/__manifest__.py
odoo/addons/partner_statement/i18n/ca.po
odoo/addons/partner_statement/i18n/de.po
odoo/addons/partner_statement/i18n/es.po
odoo/addons/partner_statement/i18n/es_AR.po
odoo/addons/partner_statement/i18n/fr.po
odoo/addons/partner_statement/i18n/hr_HR.po
odoo/addons/partner_statement/i18n/it.po
odoo/addons/partner_statement/i18n/lt.po
odoo/addons/partner_statement/i18n/nl.po
odoo/addons/partner_statement/i18n/nl_NL.po
odoo/addons/partner_statement/i18n/partner_statement.pot
odoo/addons/partner_statement/i18n/pt.po
odoo/addons/partner_statement/i18n/pt_BR.po
odoo/addons/partner_statement/i18n/ro.po
odoo/addons/partner_statement/i18n/sv.po
odoo/addons/partner_statement/i18n/tr.po
odoo/addons/partner_statement/readme/CONFIGURE.md
odoo/addons/partner_statement/readme/CONTRIBUTORS.md
odoo/addons/partner_statement/readme/DESCRIPTION.md
odoo/addons/partner_statement/readme/HISTORY.md
odoo/addons/partner_statement/readme/ROADMAP.md
odoo/addons/partner_statement/readme/USAGE.md
odoo/addons/partner_statement/report/__init__.py
odoo/addons/partner_statement/report/activity_statement.py
odoo/addons/partner_statement/report/activity_statement_xlsx.py
odoo/addons/partner_statement/report/detailed_activity_statement.py
odoo/addons/partner_statement/report/detailed_activity_statement_xlsx.py
odoo/addons/partner_statement/report/outstanding_statement.py
odoo/addons/partner_statement/report/outstanding_statement_xlsx.py
odoo/addons/partner_statement/report/report_statement_common.py
odoo/addons/partner_statement/security/ir.model.access.csv
odoo/addons/partner_statement/security/statement_security.xml
odoo/addons/partner_statement/static/description/icon.png
odoo/addons/partner_statement/static/description/index.html
odoo/addons/partner_statement/static/src/scss/layout_statement.scss
odoo/addons/partner_statement/tests/__init__.py
odoo_addon_partner_statement-19.0.1.0.0.3.dist-info/METADATA
odoo_addon_partner_statement-19.0.1.0.0.3.dist-info/WHEEL
odoo_addon_partner_statement-19.0.1.0.0.3.dist-info/top_level.txt
odoo_addon_partner_statement-19.0.1.0.0.3.dist-info/RECORD
