Metadata-Version: 2.1
Name: odoo-addon-partner_statement
Version: 19.0.1.0.0.3
Requires-Dist: odoo-addon-report_xlsx==19.0.*
Requires-Dist: odoo-addon-report_xlsx_helper==19.0.*
Requires-Dist: odoo==19.0.*
Summary: OCA Financial Reports
Home-page: https://github.com/OCA/account-financial-reporting
License: AGPL-3
Author: ForgeFlow, Odoo Community Association (OCA)
Author-email: support@odoo-community.org
Classifier: Programming Language :: Python
Classifier: Framework :: Odoo
Classifier: Framework :: Odoo :: 19.0
Classifier: License :: OSI Approved :: GNU Affero General Public License v3
